grein_loader/__init__.py
grein_loader/exceptions.py
grein_loader/load_dataset.py
grein_loader/load_overview.py
grein_loader/test.py
grein_loader/utils.py
grein_loader-0.0.6.dist-info/METADATA
grein_loader-0.0.6.dist-info/WHEEL
grein_loader-0.0.6.dist-info/licenses/LICENSE
grein_loader-0.0.6.dist-info/RECORD
