Metadata-Version: 2.4
Name: grein_loader
Version: 0.0.6
Summary: Package for loading datasets from GREIN
Project-URL: Homepage, https://github.com/grisslab/grein_loader
Project-URL: Bug Tracker, https://github.com/grisslab/grein_loader/issues
Author-email: Griss Lab <johannes.griss@meduniwien.ac.at>, Alexander Grentner <alexander.grentner@meduniwien.ac.at>
License-File: LICENSE
Classifier: License :: OSI Approved :: MIT License
Classifier: Operating System :: OS Independent
Classifier: Programming Language :: Python :: 3
Requires-Python: >=3.7
Requires-Dist: pandas
Requires-Dist: requests
